inotifyrecursive/__init__.py
inotifyrecursive/inotifyrecursive.py
inotifyrecursive-0.3.5.dist-info/LICENSE
inotifyrecursive-0.3.5.dist-info/METADATA
inotifyrecursive-0.3.5.dist-info/WHEEL
inotifyrecursive-0.3.5.dist-info/top_level.txt
inotifyrecursive-0.3.5.dist-info/RECORD
