Metadata-Version: 2.1
Name: inotifyrecursive
Version: 0.3.5
Summary: Recursive inotify watches based on inotify_simple.
Home-page: https://github.com/letorbi/inotifyrecursive
Author: Torben Haase
Author-email: git@letorbi.com
License: UNKNOWN
Platform: UNKNOWN
Classifier: Development Status :: 3 - Alpha
Classifier: Intended Audience :: Developers
Classifier: License :: OSI Approved :: GNU Lesser General Public License v3 (LGPLv3)
Classifier: Operating System :: POSIX :: Linux
Classifier: Programming Language :: Python :: 2.7
Classifier: Programming Language :: Python :: 3
Requires-Python: >=2.7, !=3.0.*, !=3.1.*
Requires-Dist: inotify-simple (>=1.3.5)
